image2excel.py
image2excel-0.0.5.dist-info/METADATA
image2excel-0.0.5.dist-info/WHEEL
image2excel-0.0.5.dist-info/top_level.txt
image2excel-0.0.5.dist-info/RECORD
