Metadata-Version: 2.1
Name: image2excel
Version: 0.0.5
Summary: converts images to excel tables
Home-page: UNKNOWN
Author-email: michel.kluger@gmail.com
License: MIT
Platform: UNKNOWN
Classifier: Programming Language :: Python :: 3
Classifier: License :: OSI Approved :: MIT License
Classifier: Operating System :: OS Independent
Requires-Python: >=3
Requires-Dist: pandas
Requires-Dist: Pillow
Requires-Dist: colormap
Requires-Dist: openpyxl
Requires-Dist: XlsxWriter
Requires-Dist: Jinja2
Requires-Dist: easydev
